cochar/__init__.py
cochar/__main__.py
cochar/character.py
cochar/cochar.py
cochar/error.py
cochar/interface.py
cochar/occup.py
cochar/skill.py
cochar/utils.py
cochar/data/occupations.json
cochar/data/popPyramid.json
cochar/data/settings.json
cochar/data/skills.json
cochar-1.0.1.dist-info/LICENSE
cochar-1.0.1.dist-info/METADATA
cochar-1.0.1.dist-info/WHEEL
cochar-1.0.1.dist-info/entry_points.txt
cochar-1.0.1.dist-info/top_level.txt
cochar-1.0.1.dist-info/RECORD
