Metadata-Version: 2.1
Name: cochar
Version: 1.0.1
Summary: Call of Cthulhu character generator
Home-page: https://github.com/ajwalkiewicz/cochar
Author: Adam Walkiewicz
License: AGPL v3
Project-URL: Documentation, https://ajwalkiewicz.github.io/cochar/_build/html/index.html
Platform: UNKNOWN
Classifier: License :: OSI Approved :: GNU Affero General Public License v3
Classifier: Operating System :: OS Independent
Classifier: Programming Language :: Python :: 3.8
Classifier: Programming Language :: Python :: 3.9
Classifier: Programming Language :: Python :: 3.10
Classifier: Programming Language :: Python :: 3.11
Requires-Dist: rname
